[
    {
        "id": "1",
        "avatar": "cliente_1.jpg",
        "thumb": "cliente_1_thumb.jpg",
        "nome": "Salão do Netto",
        "responsavel": "Antonio Netto",
        "tel1": "(11) 2227-8600",
        "cel": "(11) 98765-3789",
        "email": "nettosalao@email.com",
        "site": "http://sweethair.com.br",
        "facebook": "https://facebook.com/SweetSalonPanamby",
        "instagram": "",
        "cnpj": "19.484.983.0001-03",
        "ins_est": "12.989.933",
        "status": "ativo",
        "endereco": {
            "logradouro": "Rua Coelho Lisboa",
            "num": "556",
            "complemento": "sala 2",
            "bairro": "Tatuapé",
            "cidade": "São paulo",
            "estado": "SP"
        }
    },
    {
        "id": "2",
        "avatar": "cliente_2.jpg",
        "thumb": "cliente_2_thumb.jpg",
        "nome": "Salão Guia da Beleza",
        "responsavel": "Camila Alves",
        "tel1": "(11) 2227-8696",
        "cel": "(11) 98765-9098",
        "email": "guadabeleza@email.com",
        "site": "http://sevenlink.com.br",
        "facebook": "https://facebook.com/SweetSalonPanamby",
        "instagram": "",
        "cnpj": "19.484.978.0001-10",
        "ins_est": "12.956.933",
        "status": "ativo",
        "endereco": {
            "logradouro": "Avenida Mello Freire",
            "num": "1893",
            "complemento": "",
            "bairro": "Jardins",
            "cidade": "São paulo",
            "estado": "SP"
        }
    },
    {
        "id": "3",
        "avatar": "",
        "thumb": "",
        "nome": "Salão Ostentação Beauty",
        "responsavel": "Fabiola Seixas",
        "tel1": "(11) 4655-2130",
        "cel": "(11) 94365-9098",
        "email": "ostentacao@email.com",
        "site": "http://ostentacaosalon.com.br",
        "facebook": "https://facebook.com/sweethairbrasil",
        "instagram": "",
        "cnpj": "12.434.978.0001-10",
        "ins_est": "14.956.933",
        "status": "ativo",
        "endereco": {
            "logradouro": "logradouro Francisco Marengo",
            "num": "1493",
            "complemento": "",
            "bairro": "Carrão",
            "cidade": "São paulo",
            "estado": "SP"
        }
    },
    {
        "id": "4",
        "avatar": "cliente_2.jpg",
        "thumb": "cliente_2_thumb.jpg",
        "nome": "Henriques Cabeleireiros",
        "responsavel": "Henrique Moraes",
        "tel1": "(11) 3455-2330",
        "cel": "(11) 94355-9798",
        "email": "contato@henriquescabelos.com",
        "site": "http://henriquescabelos.com.br",
        "facebook": "https://facebook.com/sweethairbrasil",
        "instagram": "https://www.instagram.com/sweetprofessional/",
        "cnpj": "11.444.978.0001-10",
        "ins_est": "19.956.933",
        "status": "ativo",
        "endereco": {
            "logradouro": "Avenida São Luiz",
            "num": "343",
            "complemento": "loja 5",
            "bairro": "Centro",
            "cidade": "Campinas",
            "estado": "SP"
        }
    },
    {
        "id": "5",
        "avatar": "cliente_1.jpg",
        "thumb": "cliente_1_thumb.jpg",
        "nome": "Renatinhos Hairstylist",
        "responsavel": "Renato Alves",
        "tel1": "(11) 3455-2330",
        "cel": "(11) 94355-9798",
        "email": "contato@renatinhoshair.com",
        "site": "http://renatinhoshair.com.br",
        "facebook": "https://facebook.com/sweethairbrasil",
        "instagram": "https://www.instagram.com/sweetprofessional/",
        "cnpj": "18.444.668.0001-10",
        "ins_est": "12.956.933",
        "status": "ativo",
        "endereco": {
            "logradouro": "Rua Matuzalem",
            "num": "8343",
            "complemento": "",
            "bairro": "Ipiranga",
            "cidade": "São Paulo",
            "estado": "SP"
        }
    },
    {
        "id": "6",
        "avatar": "",
        "thumb": "",
        "nome": "Hair & Beauty Salon",
        "responsavel": "Michelly Palermi",
        "tel1": "(11) 4455-2330",
        "cel": "(11) 99855-9798",
        "email": "contato@hairsalon.com",
        "site": "http://hairsalonmi.com.br",
        "facebook": "https://facebook.com/sweethairbrasil",
        "instagram": "",
        "cnpj": "12.444.668.0001-10",
        "ins_est": "16.956.933",
        "status": "ativo",
        "endereco": {
            "logradouro": "Rua Alto Figueiredo",
            "num": "143",
            "complemento": "",
            "bairro": "Itaquera",
            "cidade": "São Paulo",
            "estado": "SP"
        }
    }
]